{"name":"Effects Pro","tagline":"An easy-to-use Android application to apply image filters","body":"A practical and easy-to-use Android application to apply several filters to an image at once.\r\n\r\n## Features\r\n* Applying several filters\r\n* Undoing filters one by one\r\n* Maintaining maximum image quality\r\n* Taking photos using camera or choosing from SD-Card\r\n\r\n## Filters\r\n* Boost-Up Colors\r\n* Brightness\r\n* Color Depth\r\n* Color Filter\r\n* Contrast\r\n* Emboss\r\n* Flip and Rotation\r\n* Gamma\r\n* Gaussian Blur\r\n* Grayscale\r\n* Hue\r\n* Invert\r\n* Noise\r\n* Saturation\r\n* Sepia\r\n* Sharpen\r\n* Sketch\r\n* Tint\r\n* Vignette\r\n\r\n## Screenshots\r\n![rsz_1screenshot](https://cloud.githubusercontent.com/assets/3187511/5158844/bc02e30c-7361-11e4-8563-d3f87d915b6e.jpg)\r\n![rsz_screenshot_1](https://cloud.githubusercontent.com/assets/3187511/5158851/e8af935a-7361-11e4-9576-d14cd78eeaee.jpg)\r\n![rsz_screenshot_2](https://cloud.githubusercontent.com/assets/3187511/5158846/bc56102c-7361-11e4-8f91-20b9d2fbc1d7.jpg)\r\n![rsz_screenshot_3](https://cloud.githubusercontent.com/assets/3187511/5158847/bc6150f4-7361-11e4-88d8-1789821e50fc.jpg)\r\n\r\n","google":"","note":"Don't delete this file! It's used internally to help with page regeneration."}